{
  "player": "Emilee Fitzpatrick",
  "safe_name": "Emilee_Fitzpatrick",
  "gender": "F",
  "career": {
    "era_rating": 0.0,
    "peak_rating": -0.117,
    "peak_season_id": "s28_rivals_iii",
    "active_rating": -0.117,
    "active_season_id": "s28_rivals_iii",
    "n_seasons": 2,
    "n_snapshots": 145,
    "championships": 0,
    "elim_wins": 0,
    "elim_losses": 2,
    "daily_wins": 1
  },
  "seasons": [
    {
      "season_id": "s20_cutthroat",
      "season_num": 20,
      "season_name": "Cutthroat",
      "year": 2010,
      "label": "S20 Cutthroat (2010)",
      "finish": "Eliminated in Czech Yourself Before You Wreck Yourself",
      "rating_at_end": -0.944
    },
    {
      "season_id": "s25_free_agents",
      "season_num": 25,
      "season_name": "Free Agents",
      "year": 2014,
      "label": "S25 Free Agents (2014)",
      "finish": "Eliminated in Love in the Fast Lane",
      "rating_at_end": -0.417
    }
  ],
  "timeline": [
    {
      "ranking_id": 324,
      "season_id": "s20_cutthroat",
      "rating": -0.9
    },
    {
      "ranking_id": 325,
      "season_id": "s20_cutthroat",
      "rating": -0.876
    },
    {
      "ranking_id": 326,
      "season_id": "s20_cutthroat",
      "rating": -1.282
    },
    {
      "ranking_id": 327,
      "season_id": "s20_cutthroat",
      "rating": -1.33
    },
    {
      "ranking_id": 328,
      "season_id": "s20_cutthroat",
      "rating": -1.365
    },
    {
      "ranking_id": 329,
      "season_id": "s20_cutthroat",
      "rating": -0.689
    },
    {
      "ranking_id": 330,
      "season_id": "s20_cutthroat",
      "rating": -0.741
    },
    {
      "ranking_id": 331,
      "season_id": "s20_cutthroat",
      "rating": -0.939
    },
    {
      "ranking_id": 333,
      "season_id": "s20_cutthroat",
      "rating": -0.938
    },
    {
      "ranking_id": 334,
      "season_id": "s20_cutthroat",
      "rating": -0.944
    },
    {
      "ranking_id": 335,
      "season_id": "s21_rivals",
      "rating": -0.993
    },
    {
      "ranking_id": 336,
      "season_id": "s21_rivals",
      "rating": -0.99
    },
    {
      "ranking_id": 337,
      "season_id": "s21_rivals",
      "rating": -0.999
    },
    {
      "ranking_id": 338,
      "season_id": "s21_rivals",
      "rating": -0.99
    },
    {
      "ranking_id": 339,
      "season_id": "s21_rivals",
      "rating": -0.997
    },
    {
      "ranking_id": 340,
      "season_id": "s21_rivals",
      "rating": -1.082
    },
    {
      "ranking_id": 341,
      "season_id": "s21_rivals",
      "rating": -1.082
    },
    {
      "ranking_id": 342,
      "season_id": "s21_rivals",
      "rating": -1.058
    },
    {
      "ranking_id": 343,
      "season_id": "s21_rivals",
      "rating": -1.101
    },
    {
      "ranking_id": 344,
      "season_id": "s21_rivals",
      "rating": -1.128
    },
    {
      "ranking_id": 345,
      "season_id": "s21_rivals",
      "rating": -1.145
    },
    {
      "ranking_id": 346,
      "season_id": "s21_rivals",
      "rating": -1.145
    },
    {
      "ranking_id": 347,
      "season_id": "s21_rivals",
      "rating": -1.139
    },
    {
      "ranking_id": 348,
      "season_id": "s21_rivals",
      "rating": -1.152
    },
    {
      "ranking_id": 349,
      "season_id": "s21_rivals",
      "rating": -1.157
    },
    {
      "ranking_id": 350,
      "season_id": "s21_rivals",
      "rating": -1.157
    },
    {
      "ranking_id": 351,
      "season_id": "s21_rivals",
      "rating": -1.144
    },
    {
      "ranking_id": 352,
      "season_id": "s21_rivals",
      "rating": -1.144
    },
    {
      "ranking_id": 353,
      "season_id": "s21_rivals",
      "rating": -1.144
    },
    {
      "ranking_id": 354,
      "season_id": "s21_rivals",
      "rating": -1.165
    },
    {
      "ranking_id": 355,
      "season_id": "s21_rivals",
      "rating": -1.197
    },
    {
      "ranking_id": 356,
      "season_id": "s21_rivals",
      "rating": -1.163
    },
    {
      "ranking_id": 357,
      "season_id": "s21_rivals",
      "rating": -1.108
    },
    {
      "ranking_id": 358,
      "season_id": "s21_rivals",
      "rating": -1.003
    },
    {
      "ranking_id": 359,
      "season_id": "s21_rivals",
      "rating": -0.99
    },
    {
      "ranking_id": 360,
      "season_id": "s21_rivals",
      "rating": -0.99
    },
    {
      "ranking_id": 361,
      "season_id": "s21_rivals",
      "rating": -0.99
    },
    {
      "ranking_id": 362,
      "season_id": "s21_rivals",
      "rating": -0.962
    },
    {
      "ranking_id": 363,
      "season_id": "s21_rivals",
      "rating": -1.151
    },
    {
      "ranking_id": 364,
      "season_id": "s22_battle_of_the_exes",
      "rating": -1.121
    },
    {
      "ranking_id": 365,
      "season_id": "s22_battle_of_the_exes",
      "rating": -1.065
    },
    {
      "ranking_id": 366,
      "season_id": "s22_battle_of_the_exes",
      "rating": -0.955
    },
    {
      "ranking_id": 368,
      "season_id": "s22_battle_of_the_exes",
      "rating": -0.895
    },
    {
      "ranking_id": 369,
      "season_id": "s22_battle_of_the_exes",
      "rating": -0.895
    },
    {
      "ranking_id": 370,
      "season_id": "s22_battle_of_the_exes",
      "rating": -0.905
    },
    {
      "ranking_id": 372,
      "season_id": "s22_battle_of_the_exes",
      "rating": -0.906
    },
    {
      "ranking_id": 373,
      "season_id": "s22_battle_of_the_exes",
      "rating": -1.001
    },
    {
      "ranking_id": 374,
      "season_id": "s22_battle_of_the_exes",
      "rating": -1.004
    },
    {
      "ranking_id": 376,
      "season_id": "s22_battle_of_the_exes",
      "rating": -1.053
    },
    {
      "ranking_id": 378,
      "season_id": "s22_battle_of_the_exes",
      "rating": -1.082
    },
    {
      "ranking_id": 380,
      "season_id": "s22_battle_of_the_exes",
      "rating": -1.079
    },
    {
      "ranking_id": 381,
      "season_id": "s22_battle_of_the_exes",
      "rating": -1.077
    },
    {
      "ranking_id": 382,
      "season_id": "s22_battle_of_the_exes",
      "rating": -1.077
    },
    {
      "ranking_id": 384,
      "season_id": "s22_battle_of_the_exes",
      "rating": -1.089
    },
    {
      "ranking_id": 386,
      "season_id": "s22_battle_of_the_exes",
      "rating": -1.044
    },
    {
      "ranking_id": 387,
      "season_id": "s22_battle_of_the_exes",
      "rating": -1.041
    },
    {
      "ranking_id": 388,
      "season_id": "s22_battle_of_the_exes",
      "rating": -1.044
    },
    {
      "ranking_id": 389,
      "season_id": "s22_battle_of_the_exes",
      "rating": -1.033
    },
    {
      "ranking_id": 390,
      "season_id": "s22_battle_of_the_exes",
      "rating": -1.019
    },
    {
      "ranking_id": 392,
      "season_id": "s22_battle_of_the_exes",
      "rating": -1.001
    },
    {
      "ranking_id": 393,
      "season_id": "s22_battle_of_the_exes",
      "rating": -0.936
    },
    {
      "ranking_id": 394,
      "season_id": "s22_battle_of_the_exes",
      "rating": -0.936
    },
    {
      "ranking_id": 396,
      "season_id": "s22_battle_of_the_exes",
      "rating": -0.744
    },
    {
      "ranking_id": 397,
      "season_id": "s23_battle_of_the_seasons_2012",
      "rating": -0.552
    },
    {
      "ranking_id": 400,
      "season_id": "s23_battle_of_the_seasons_2012",
      "rating": -0.548
    },
    {
      "ranking_id": 401,
      "season_id": "s23_battle_of_the_seasons_2012",
      "rating": -0.531
    },
    {
      "ranking_id": 402,
      "season_id": "s23_battle_of_the_seasons_2012",
      "rating": -0.517
    },
    {
      "ranking_id": 403,
      "season_id": "s23_battle_of_the_seasons_2012",
      "rating": -0.515
    },
    {
      "ranking_id": 405,
      "season_id": "s23_battle_of_the_seasons_2012",
      "rating": -0.527
    },
    {
      "ranking_id": 408,
      "season_id": "s23_battle_of_the_seasons_2012",
      "rating": -0.497
    },
    {
      "ranking_id": 409,
      "season_id": "s23_battle_of_the_seasons_2012",
      "rating": -0.574
    },
    {
      "ranking_id": 412,
      "season_id": "s23_battle_of_the_seasons_2012",
      "rating": -0.513
    },
    {
      "ranking_id": 413,
      "season_id": "s23_battle_of_the_seasons_2012",
      "rating": -0.523
    },
    {
      "ranking_id": 414,
      "season_id": "s23_battle_of_the_seasons_2012",
      "rating": -0.52
    },
    {
      "ranking_id": 415,
      "season_id": "s23_battle_of_the_seasons_2012",
      "rating": -0.502
    },
    {
      "ranking_id": 417,
      "season_id": "s23_battle_of_the_seasons_2012",
      "rating": -0.462
    },
    {
      "ranking_id": 418,
      "season_id": "s23_battle_of_the_seasons_2012",
      "rating": -0.462
    },
    {
      "ranking_id": 419,
      "season_id": "s23_battle_of_the_seasons_2012",
      "rating": -0.464
    },
    {
      "ranking_id": 421,
      "season_id": "s23_battle_of_the_seasons_2012",
      "rating": -0.51
    },
    {
      "ranking_id": 476,
      "season_id": "s25_free_agents",
      "rating": -0.373
    },
    {
      "ranking_id": 477,
      "season_id": "s25_free_agents",
      "rating": -0.355
    },
    {
      "ranking_id": 478,
      "season_id": "s25_free_agents",
      "rating": -0.348
    },
    {
      "ranking_id": 479,
      "season_id": "s25_free_agents",
      "rating": -0.343
    },
    {
      "ranking_id": 480,
      "season_id": "s25_free_agents",
      "rating": -0.327
    },
    {
      "ranking_id": 481,
      "season_id": "s25_free_agents",
      "rating": -0.327
    },
    {
      "ranking_id": 482,
      "season_id": "s25_free_agents",
      "rating": -0.313
    },
    {
      "ranking_id": 483,
      "season_id": "s25_free_agents",
      "rating": -0.314
    },
    {
      "ranking_id": 484,
      "season_id": "s25_free_agents",
      "rating": -0.313
    },
    {
      "ranking_id": 485,
      "season_id": "s25_free_agents",
      "rating": -0.306
    },
    {
      "ranking_id": 486,
      "season_id": "s25_free_agents",
      "rating": -0.364
    },
    {
      "ranking_id": 488,
      "season_id": "s25_free_agents",
      "rating": -0.346
    },
    {
      "ranking_id": 489,
      "season_id": "s25_free_agents",
      "rating": -0.346
    },
    {
      "ranking_id": 490,
      "season_id": "s25_free_agents",
      "rating": -0.346
    },
    {
      "ranking_id": 491,
      "season_id": "s25_free_agents",
      "rating": -0.316
    },
    {
      "ranking_id": 492,
      "season_id": "s25_free_agents",
      "rating": -0.324
    },
    {
      "ranking_id": 493,
      "season_id": "s25_free_agents",
      "rating": -0.331
    },
    {
      "ranking_id": 494,
      "season_id": "s25_free_agents",
      "rating": -0.331
    },
    {
      "ranking_id": 496,
      "season_id": "s25_free_agents",
      "rating": -0.327
    },
    {
      "ranking_id": 497,
      "season_id": "s25_free_agents",
      "rating": -0.417
    },
    {
      "ranking_id": 498,
      "season_id": "s26_battle_of_the_exes_ii",
      "rating": -0.304
    },
    {
      "ranking_id": 501,
      "season_id": "s26_battle_of_the_exes_ii",
      "rating": -0.328
    },
    {
      "ranking_id": 502,
      "season_id": "s26_battle_of_the_exes_ii",
      "rating": -0.424
    },
    {
      "ranking_id": 505,
      "season_id": "s26_battle_of_the_exes_ii",
      "rating": -0.398
    },
    {
      "ranking_id": 506,
      "season_id": "s26_battle_of_the_exes_ii",
      "rating": -0.435
    },
    {
      "ranking_id": 509,
      "season_id": "s26_battle_of_the_exes_ii",
      "rating": -0.419
    },
    {
      "ranking_id": 510,
      "season_id": "s26_battle_of_the_exes_ii",
      "rating": -0.41
    },
    {
      "ranking_id": 511,
      "season_id": "s26_battle_of_the_exes_ii",
      "rating": -0.406
    },
    {
      "ranking_id": 512,
      "season_id": "s26_battle_of_the_exes_ii",
      "rating": -0.411
    },
    {
      "ranking_id": 514,
      "season_id": "s26_battle_of_the_exes_ii",
      "rating": -0.388
    },
    {
      "ranking_id": 517,
      "season_id": "s26_battle_of_the_exes_ii",
      "rating": -0.393
    },
    {
      "ranking_id": 518,
      "season_id": "s26_battle_of_the_exes_ii",
      "rating": -0.4
    },
    {
      "ranking_id": 519,
      "season_id": "s26_battle_of_the_exes_ii",
      "rating": -0.41
    },
    {
      "ranking_id": 520,
      "season_id": "s26_battle_of_the_exes_ii",
      "rating": -0.39
    },
    {
      "ranking_id": 522,
      "season_id": "s26_battle_of_the_exes_ii",
      "rating": -0.386
    },
    {
      "ranking_id": 523,
      "season_id": "s26_battle_of_the_exes_ii",
      "rating": -0.361
    },
    {
      "ranking_id": 524,
      "season_id": "s26_battle_of_the_exes_ii",
      "rating": -0.335
    },
    {
      "ranking_id": 526,
      "season_id": "s26_battle_of_the_exes_ii",
      "rating": -0.321
    },
    {
      "ranking_id": 527,
      "season_id": "s26_battle_of_the_exes_ii",
      "rating": -0.359
    },
    {
      "ranking_id": 528,
      "season_id": "s26_battle_of_the_exes_ii",
      "rating": -0.427
    },
    {
      "ranking_id": 530,
      "season_id": "s26_battle_of_the_exes_ii",
      "rating": -0.421
    },
    {
      "ranking_id": 531,
      "season_id": "s26_battle_of_the_exes_ii",
      "rating": -0.441
    },
    {
      "ranking_id": 532,
      "season_id": "s26_battle_of_the_exes_ii",
      "rating": -0.439
    },
    {
      "ranking_id": 534,
      "season_id": "s26_battle_of_the_exes_ii",
      "rating": -0.433
    },
    {
      "ranking_id": 537,
      "season_id": "s26_battle_of_the_exes_ii",
      "rating": -0.439
    },
    {
      "ranking_id": 538,
      "season_id": "s26_battle_of_the_exes_ii",
      "rating": -0.424
    },
    {
      "ranking_id": 539,
      "season_id": "s27_battle_of_the_bloodlines",
      "rating": -0.22
    },
    {
      "ranking_id": 540,
      "season_id": "s27_battle_of_the_bloodlines",
      "rating": -0.269
    },
    {
      "ranking_id": 541,
      "season_id": "s27_battle_of_the_bloodlines",
      "rating": -0.296
    },
    {
      "ranking_id": 542,
      "season_id": "s27_battle_of_the_bloodlines",
      "rating": -0.296
    },
    {
      "ranking_id": 543,
      "season_id": "s27_battle_of_the_bloodlines",
      "rating": -0.29
    },
    {
      "ranking_id": 544,
      "season_id": "s27_battle_of_the_bloodlines",
      "rating": -0.287
    },
    {
      "ranking_id": 545,
      "season_id": "s27_battle_of_the_bloodlines",
      "rating": -0.29
    },
    {
      "ranking_id": 546,
      "season_id": "s27_battle_of_the_bloodlines",
      "rating": -0.29
    },
    {
      "ranking_id": 547,
      "season_id": "s27_battle_of_the_bloodlines",
      "rating": -0.29
    },
    {
      "ranking_id": 549,
      "season_id": "s27_battle_of_the_bloodlines",
      "rating": -0.273
    },
    {
      "ranking_id": 551,
      "season_id": "s27_battle_of_the_bloodlines",
      "rating": -0.25
    },
    {
      "ranking_id": 552,
      "season_id": "s27_battle_of_the_bloodlines",
      "rating": -0.253
    },
    {
      "ranking_id": 553,
      "season_id": "s28_rivals_iii",
      "rating": -0.21
    },
    {
      "ranking_id": 556,
      "season_id": "s28_rivals_iii",
      "rating": -0.192
    },
    {
      "ranking_id": 557,
      "season_id": "s28_rivals_iii",
      "rating": -0.23
    },
    {
      "ranking_id": 560,
      "season_id": "s28_rivals_iii",
      "rating": -0.185
    },
    {
      "ranking_id": 561,
      "season_id": "s28_rivals_iii",
      "rating": -0.168
    },
    {
      "ranking_id": 562,
      "season_id": "s28_rivals_iii",
      "rating": -0.168
    },
    {
      "ranking_id": 563,
      "season_id": "s28_rivals_iii",
      "rating": -0.167
    },
    {
      "ranking_id": 565,
      "season_id": "s28_rivals_iii",
      "rating": -0.117
    }
  ]
}