{
  "player": "Joss Mooney",
  "safe_name": "Joss_Mooney",
  "gender": "M",
  "career": {
    "era_rating": 0.9,
    "peak_rating": 0.768,
    "peak_season_id": "s33_war_of_the_worlds",
    "active_rating": -0.818,
    "active_season_id": "s38_ride_or_dies",
    "n_seasons": 3,
    "n_snapshots": 145,
    "championships": 0,
    "elim_wins": 6,
    "elim_losses": 1,
    "daily_wins": 3
  },
  "seasons": [
    {
      "season_id": "s34_war_of_the_worlds_2",
      "season_num": 34,
      "season_name": "War of the Worlds 2",
      "year": 2019,
      "label": "S34 War of the Worlds 2 (2019)",
      "finish": "Eliminated in Dee-Day",
      "finish_label": "Eliminated",
      "finish_episode": "Dee-Day",
      "elim_position": null,
      "elim_total": null,
      "rating_at_end": 0.299,
      "partner": "",
      "partners_history": [],
      "team": "Team UK",
      "forced_exit": false
    },
    {
      "season_id": "s32_final_reckoning",
      "season_num": 32,
      "season_name": "Final Reckoning",
      "year": 2018,
      "label": "S32 Final Reckoning (2018)",
      "finish": "Runners-Up in Who Wants to Be a Millionaire?",
      "finish_label": "Runner-up",
      "finish_episode": "Who Wants to Be a Millionaire?",
      "elim_position": null,
      "elim_total": null,
      "rating_at_end": 0.562,
      "partner": "Sylvia Elsrode",
      "partners_history": [],
      "team": "",
      "forced_exit": false
    },
    {
      "season_id": "s31_vendettas",
      "season_num": 31,
      "season_name": "Vendettas",
      "year": 2018,
      "label": "S31 Vendettas (2018)",
      "finish": "Eliminated in Mercenaries of Mayhem",
      "finish_label": "Eliminated",
      "finish_episode": "Mercenaries of Mayhem",
      "elim_position": 9,
      "elim_total": 9,
      "rating_at_end": -0.484,
      "partner": "",
      "partners_history": [],
      "team": "",
      "forced_exit": false
    }
  ],
  "timeline": [
    {
      "ranking_id": 647,
      "season_id": "s31_vendettas",
      "rating": -0.758
    },
    {
      "ranking_id": 648,
      "season_id": "s31_vendettas",
      "rating": -0.661
    },
    {
      "ranking_id": 649,
      "season_id": "s31_vendettas",
      "rating": -0.672
    },
    {
      "ranking_id": 650,
      "season_id": "s31_vendettas",
      "rating": -0.712
    },
    {
      "ranking_id": 651,
      "season_id": "s31_vendettas",
      "rating": -0.725
    },
    {
      "ranking_id": 652,
      "season_id": "s31_vendettas",
      "rating": -0.717
    },
    {
      "ranking_id": 653,
      "season_id": "s31_vendettas",
      "rating": -0.74
    },
    {
      "ranking_id": 654,
      "season_id": "s31_vendettas",
      "rating": -0.684
    },
    {
      "ranking_id": 655,
      "season_id": "s31_vendettas",
      "rating": -0.609
    },
    {
      "ranking_id": 658,
      "season_id": "s31_vendettas",
      "rating": -0.606
    },
    {
      "ranking_id": 661,
      "season_id": "s31_vendettas",
      "rating": -0.558
    },
    {
      "ranking_id": 662,
      "season_id": "s31_vendettas",
      "rating": -0.484
    },
    {
      "ranking_id": 663,
      "season_id": "s32_final_reckoning",
      "rating": -0.494
    },
    {
      "ranking_id": 665,
      "season_id": "s32_final_reckoning",
      "rating": -0.452
    },
    {
      "ranking_id": 667,
      "season_id": "s32_final_reckoning",
      "rating": 0.218
    },
    {
      "ranking_id": 670,
      "season_id": "s32_final_reckoning",
      "rating": 0.125
    },
    {
      "ranking_id": 671,
      "season_id": "s32_final_reckoning",
      "rating": 0.148
    },
    {
      "ranking_id": 672,
      "season_id": "s32_final_reckoning",
      "rating": 0.148
    },
    {
      "ranking_id": 675,
      "season_id": "s32_final_reckoning",
      "rating": 0.156
    },
    {
      "ranking_id": 677,
      "season_id": "s32_final_reckoning",
      "rating": 0.156
    },
    {
      "ranking_id": 679,
      "season_id": "s32_final_reckoning",
      "rating": 0.103
    },
    {
      "ranking_id": 680,
      "season_id": "s32_final_reckoning",
      "rating": 0.141
    },
    {
      "ranking_id": 681,
      "season_id": "s32_final_reckoning",
      "rating": 0.141
    },
    {
      "ranking_id": 682,
      "season_id": "s32_final_reckoning",
      "rating": 0.124
    },
    {
      "ranking_id": 683,
      "season_id": "s32_final_reckoning",
      "rating": 0.125
    },
    {
      "ranking_id": 684,
      "season_id": "s32_final_reckoning",
      "rating": 0.118
    },
    {
      "ranking_id": 686,
      "season_id": "s32_final_reckoning",
      "rating": 0.098
    },
    {
      "ranking_id": 687,
      "season_id": "s32_final_reckoning",
      "rating": 0.079
    },
    {
      "ranking_id": 691,
      "season_id": "s32_final_reckoning",
      "rating": 0.511
    },
    {
      "ranking_id": 692,
      "season_id": "s32_final_reckoning",
      "rating": 0.663
    },
    {
      "ranking_id": 695,
      "season_id": "s32_final_reckoning",
      "rating": 0.635
    },
    {
      "ranking_id": 697,
      "season_id": "s32_final_reckoning",
      "rating": 0.632
    },
    {
      "ranking_id": 698,
      "season_id": "s32_final_reckoning",
      "rating": 0.631
    },
    {
      "ranking_id": 699,
      "season_id": "s32_final_reckoning",
      "rating": 0.435
    },
    {
      "ranking_id": 702,
      "season_id": "s32_final_reckoning",
      "rating": 0.452
    },
    {
      "ranking_id": 703,
      "season_id": "s32_final_reckoning",
      "rating": 0.562
    },
    {
      "ranking_id": 744,
      "season_id": "s34_war_of_the_worlds_2",
      "rating": 0.611
    },
    {
      "ranking_id": 745,
      "season_id": "s34_war_of_the_worlds_2",
      "rating": 0.594
    },
    {
      "ranking_id": 746,
      "season_id": "s34_war_of_the_worlds_2",
      "rating": 0.584
    },
    {
      "ranking_id": 747,
      "season_id": "s34_war_of_the_worlds_2",
      "rating": 0.584
    },
    {
      "ranking_id": 748,
      "season_id": "s34_war_of_the_worlds_2",
      "rating": 0.558
    },
    {
      "ranking_id": 749,
      "season_id": "s34_war_of_the_worlds_2",
      "rating": 0.554
    },
    {
      "ranking_id": 750,
      "season_id": "s34_war_of_the_worlds_2",
      "rating": 0.603
    },
    {
      "ranking_id": 751,
      "season_id": "s34_war_of_the_worlds_2",
      "rating": 0.597
    },
    {
      "ranking_id": 753,
      "season_id": "s34_war_of_the_worlds_2",
      "rating": 0.486
    },
    {
      "ranking_id": 754,
      "season_id": "s34_war_of_the_worlds_2",
      "rating": 0.523
    },
    {
      "ranking_id": 755,
      "season_id": "s34_war_of_the_worlds_2",
      "rating": 0.516
    },
    {
      "ranking_id": 756,
      "season_id": "s34_war_of_the_worlds_2",
      "rating": 0.506
    },
    {
      "ranking_id": 757,
      "season_id": "s34_war_of_the_worlds_2",
      "rating": 0.415
    },
    {
      "ranking_id": 758,
      "season_id": "s34_war_of_the_worlds_2",
      "rating": 0.412
    },
    {
      "ranking_id": 759,
      "season_id": "s34_war_of_the_worlds_2",
      "rating": 0.299
    }
  ]
}