{
  "player": "Kaz Crossley",
  "safe_name": "Kaz_Crossley",
  "gender": "F",
  "career": {
    "era_rating": 0.0,
    "peak_rating": -0.636,
    "peak_season_id": "s39_battle_for_a_new_champion",
    "active_rating": -0.554,
    "active_season_id": "s40_battle_of_the_eras",
    "n_seasons": 1,
    "n_snapshots": 2,
    "championships": 0,
    "finals_reached": 0,
    "pre_anchor_titles": 0,
    "elim_wins": 0,
    "elim_losses": 1,
    "daily_wins": 0
  },
  "seasons": [
    {
      "season_id": "s39_battle_for_a_new_champion",
      "season_num": 39,
      "season_name": "Battle for a New Champion",
      "year": 2023,
      "label": "S39 Battle for a New Champion (2023)",
      "finish": "Champion Mercenary",
      "finish_label": "Mercenary",
      "finish_episode": "",
      "elim_position": 3,
      "elim_total": 11,
      "eliminated_by": [
        "Big T Fazakerley"
      ],
      "rating_at_end": -0.636,
      "rank": 16,
      "rank_total": 17,
      "daily_wins": 0,
      "elim_wins": 0,
      "elim_losses": 1,
      "partner": "",
      "partners_history": [],
      "team": "",
      "forced_exit": false
    }
  ],
  "timeline": [
    {
      "ranking_id": 970,
      "season_id": "s39_battle_for_a_new_champion",
      "rating": -0.636
    }
  ]
}