{
  "player": "MJ Garrett",
  "safe_name": "MJ_Garrett",
  "gender": "M",
  "career": {
    "era_rating": 0.7,
    "peak_rating": 0.622,
    "peak_season_id": "s11_the_gauntlet_2",
    "active_rating": 0.362,
    "active_season_id": "s20_cutthroat",
    "n_seasons": 3,
    "n_snapshots": 9,
    "championships": 1,
    "elim_wins": 2,
    "elim_losses": 2,
    "daily_wins": 3
  },
  "seasons": [
    {
      "season_id": "s17_the_duel_ii",
      "season_num": 17,
      "season_name": "The Duel II",
      "year": 2009,
      "label": "S17 The Duel II (2009)",
      "finish": "Eliminated in Duel or Die",
      "finish_label": "Eliminated",
      "finish_episode": "Duel or Die",
      "elim_position": 6,
      "elim_total": 10,
      "rating_at_end": 0.075,
      "partner": "",
      "partners_history": [],
      "team": "",
      "forced_exit": false
    },
    {
      "season_id": "s15_the_gauntlet_iii",
      "season_num": 15,
      "season_name": "The Gauntlet III",
      "year": 2008,
      "label": "S15 The Gauntlet III (2008)",
      "finish": "Eliminated in All Alone",
      "finish_label": "Eliminated",
      "finish_episode": "All Alone",
      "elim_position": 6,
      "elim_total": 8,
      "rating_at_end": -0.305,
      "partner": "",
      "partners_history": [],
      "team": "Rookies",
      "forced_exit": false
    },
    {
      "season_id": "s11_the_gauntlet_2",
      "season_num": 11,
      "season_name": "The Gauntlet 2",
      "year": 2005,
      "label": "S11 The Gauntlet 2 (2005)",
      "finish": "Winners in Don't Bet on It",
      "finish_label": "Champion",
      "finish_episode": "Don't Bet on It",
      "elim_position": null,
      "elim_total": null,
      "rating_at_end": 0.622,
      "partner": "",
      "partners_history": [],
      "team": "Rookies",
      "forced_exit": false
    }
  ],
  "timeline": [
    {
      "ranking_id": 147,
      "season_id": "s11_the_gauntlet_2",
      "rating": 0.622
    },
    {
      "ranking_id": 259,
      "season_id": "s15_the_gauntlet_iii",
      "rating": -0.305
    },
    {
      "ranking_id": 284,
      "season_id": "s17_the_duel_ii",
      "rating": 0.075
    }
  ]
}