{
  "season_id": "s16_the_island",
  "season_num": 16,
  "season_name": "The Island",
  "year": 2008,
  "label": "S16 The Island (2008)",
  "standings_at_end": {
    "M": [
      {
        "rank": 1,
        "player": "Derrick Kosinski",
        "rating": 0.536,
        "n_events": 85,
        "finish": "Winners in infobox"
      },
      {
        "rank": 2,
        "player": "Abram Boise",
        "rating": 0.449,
        "n_events": 41,
        "finish": "Eliminated in Calling It Quits"
      },
      {
        "rank": 3,
        "player": "Kenny Santucci",
        "rating": 0.42,
        "n_events": 118,
        "finish": "Winners in infobox"
      },
      {
        "rank": 4,
        "player": "Ryan Kehoe",
        "rating": -0.15,
        "n_events": 99,
        "finish": "Runner-Up in Sailing to Victory"
      },
      {
        "rank": 5,
        "player": "Dan Walsh",
        "rating": -0.154,
        "n_events": 12,
        "finish": "Eliminated in Sailing to Victory"
      },
      {
        "rank": 6,
        "player": "Johnny Bananas",
        "rating": -0.159,
        "n_events": 87,
        "finish": "Winners in infobox"
      },
      {
        "rank": 7,
        "player": "Tyri Ballard-Brown",
        "rating": -0.506,
        "n_events": 67,
        "finish": "Eliminated in Ev vs. the Island"
      },
      {
        "rank": 8,
        "player": "Cohutta Grindstaff",
        "rating": -0.642,
        "n_events": 11,
        "finish": "Eliminated in Island King"
      },
      {
        "rank": 9,
        "player": "Dave Malinosky",
        "rating": -0.887,
        "n_events": 11,
        "finish": "Quit in Calling It Quits"
      },
      {
        "rank": 10,
        "player": "Dunbar Merrill",
        "rating": -0.887,
        "n_events": 11,
        "finish": "Eliminated in Sailing to Victory"
      }
    ],
    "F": [
      {
        "rank": 1,
        "player": "Johanna Botta",
        "rating": 0.43,
        "n_events": 69,
        "finish": "Eliminated in Sailing to Victory"
      },
      {
        "rank": 2,
        "player": "Evelyn Smith",
        "rating": 0.338,
        "n_events": 106,
        "finish": "Winners in infobox"
      },
      {
        "rank": 3,
        "player": "Tonya Cooley",
        "rating": 0.218,
        "n_events": 52,
        "finish": "Eliminated in Welcome to the Island"
      },
      {
        "rank": 4,
        "player": "Robin Hibbard",
        "rating": -0.169,
        "n_events": 72,
        "finish": "Runners-Up in Sailing to Victory"
      },
      {
        "rank": 5,
        "player": "Paula Meronek",
        "rating": -0.221,
        "n_events": 88,
        "finish": "Runners-Up in Sailing to Victory"
      },
      {
        "rank": 6,
        "player": "Rachel Robinson",
        "rating": -0.374,
        "n_events": 21,
        "finish": "Eliminated in Girl Fight"
      },
      {
        "rank": 7,
        "player": "Jenn Grijalva",
        "rating": -0.642,
        "n_events": 37,
        "finish": "Runners-Up in Sailing to Victory"
      },
      {
        "rank": 8,
        "player": "Colie",
        "rating": -1.051,
        "n_events": 25,
        "finish": "Eliminated in Down to the Wire"
      },
      {
        "rank": 9,
        "player": "Ashli Robson",
        "rating": -1.052,
        "n_events": 13,
        "finish": "Eliminated in Are You a Quitter?"
      },
      {
        "rank": 10,
        "player": "KellyAnne Judd",
        "rating": -1.052,
        "n_events": 13,
        "finish": "Eliminated in Sailing to Victory"
      }
    ]
  }
}